django_grainy/__init__.py
django_grainy/admin.py
django_grainy/apps.py
django_grainy/backends.py
django_grainy/conf.py
django_grainy/const.py
django_grainy/decorators.py
django_grainy/exceptions.py
django_grainy/fields.py
django_grainy/forms.py
django_grainy/handlers.py
django_grainy/helpers.py
django_grainy/models.py
django_grainy/remote.py
django_grainy/rest.py
django_grainy/tests.py
django_grainy/util.py
django_grainy/views.py
django_grainy/migrations/0001_initial.py
django_grainy/migrations/__init__.py
django_grainy/static/grainy/grainy.js
django_grainy/templates/django_grainy/forms/widgets/bitmask_select.html
django_grainy-2.0.1.dist-info/METADATA
django_grainy-2.0.1.dist-info/WHEEL
django_grainy-2.0.1.dist-info/licenses/LICENSE
django_grainy-2.0.1.dist-info/RECORD
