Metadata-Version: 2.3
Name: django-grainy
Version: 2.0.1
Summary: granular permissions for django
Author-email: 20C <code@20c.com>
License:                                  Apache License
License-File: LICENSE
Classifier: Development Status :: 5 - Production/Stable
Classifier: License :: OSI Approved :: Apache Software License
Classifier: Programming Language :: Python :: 3.8
Classifier: Programming Language :: Python :: 3.9
Classifier: Programming Language :: Python :: 3.10
Classifier: Programming Language :: Python :: 3.11
Classifier: Programming Language :: Python :: 3.12
Requires-Python: <4.0,>=3.8
Requires-Dist: django>=3.2
Requires-Dist: djangorestframework>=3
Requires-Dist: grainy>=1.7
Provides-Extra: dev
Requires-Dist: coverage>=4.1; extra == 'dev'
Requires-Dist: ctl>=1; extra == 'dev'
Requires-Dist: jinja2>=3; extra == 'dev'
Requires-Dist: markdown-include>=0.5; extra == 'dev'
Requires-Dist: mkdocs>=1.2.3; extra == 'dev'
Requires-Dist: pre-commit>=2.13.0; extra == 'dev'
Requires-Dist: pytest-cov>=2.2.1; extra == 'dev'
Requires-Dist: pytest-django>=3.8.0; extra == 'dev'
Requires-Dist: pytest>=6.0.1; extra == 'dev'
Requires-Dist: pyupgrade>=2.34.0; extra == 'dev'
Requires-Dist: ruff>=0.1; extra == 'dev'
Requires-Dist: tmpl>=1; extra == 'dev'
Requires-Dist: tox-gh-actions>=2.9.1; extra == 'dev'
Requires-Dist: tox-uv>=1.13.0; extra == 'dev'
Requires-Dist: tox>=3.25.0; extra == 'dev'
